[  {    "success": {      "fields": {        "Success 200": [          {            "group": "Success 200",            "optional": false,            "field": "varname1",            "description": "<p>No type.</p> "          },          {            "group": "Success 200",            "type": "<p>String</p> ",            "optional": false,            "field": "varname2",            "description": "<p>With type.</p> "          }        ]      }    },    "type": "",    "url": "",    "version": "0.0.0",    "filename": "nssoft-template/other/apidoc/template/main.js",    "group": "_Users_xuliguo_Workspaces_Eclipse_LUNA_nssoft_template_other_apidoc_template_main_js",    "groupTitle": "_Users_xuliguo_Workspaces_Eclipse_LUNA_nssoft_template_other_apidoc_template_main_js",    "name": ""  },  {    "success": {      "fields": {        "Success 200": [          {            "group": "Success 200",            "optional": false,            "field": "varname1",            "description": "<p>No type.</p> "          },          {            "group": "Success 200",            "type": "<p>String</p> ",            "optional": false,            "field": "varname2",            "description": "<p>With type.</p> "          }        ]      }    },    "type": "",    "url": "",    "version": "0.0.0",    "filename": "nssoft-template/src/main/webapp/static-resources/apidoc/main.js",    "group": "_Users_xuliguo_Workspaces_Eclipse_LUNA_nssoft_template_src_main_webapp_static_resources_apidoc_main_js",    "groupTitle": "_Users_xuliguo_Workspaces_Eclipse_LUNA_nssoft_template_src_main_webapp_static_resources_apidoc_main_js",    "name": ""  },  {    "type": "post",    "url": "/v1/api/test/sample/deleteRow.json",    "title": "DeleteRow.java",    "version": "1.0.0",    "name": "DeleteRow_java",    "group": "com_nssoft_api_test_sample",    "parameter": {      "fields": {        "Parameter": [          {            "group": "Parameter",            "type": "<p>String</p> ",            "optional": true,            "field": "a",            "description": "<p>可选参数x.</p> "          },          {            "group": "Parameter",            "type": "<p>Number</p> ",            "optional": true,            "field": "b",            "defaultValue": "18",            "description": "<p>可选参数的默认值为'18'.</p> "          },          {            "group": "Parameter",            "type": "<p>String</p> ",            "optional": false,            "field": "c",            "description": "<p>必填参数z.</p> "          },          {            "group": "Parameter",            "type": "<p>String</p> ",            "optional": false,            "field": "d",            "defaultValue": "D",            "description": "<p>必填参数的默认值为'D'.</p> "          }        ]      }    },    "sampleRequest": [      {        "url": "/v1/api/test/sample/deleteRow.json"      }    ],    "filename": "nssoft-template/src/main/java/com/nssoft/api/test/sample/DeleteRow.java",    "groupTitle": "com_nssoft_api_test_sample"  },  {    "type": "post",    "url": "/v1/api/test/sample/detail.json",    "title": "Detail.java",    "version": "1.0.0",    "name": "Detail_java",    "group": "com_nssoft_api_test_sample",    "parameter": {      "fields": {        "Parameter": [          {            "group": "Parameter",            "type": "<p>String</p> ",            "optional": true,            "field": "a",            "description": "<p>可选参数x.</p> "          },          {            "group": "Parameter",            "type": "<p>Number</p> ",            "optional": true,            "field": "b",            "defaultValue": "18",            "description": "<p>可选参数的默认值为'18'.</p> "          },          {            "group": "Parameter",            "type": "<p>String</p> ",            "optional": false,            "field": "c",            "description": "<p>必填参数z.</p> "          },          {            "group": "Parameter",            "type": "<p>String</p> ",            "optional": false,            "field": "d",            "defaultValue": "D",            "description": "<p>必填参数的默认值为'D'.</p> "          }        ]      }    },    "sampleRequest": [      {        "url": "/v1/api/test/sample/detail.json"      }    ],    "filename": "nssoft-template/src/main/java/com/nssoft/api/test/sample/Detail.java",    "groupTitle": "com_nssoft_api_test_sample"  },  {    "type": "post",    "url": "/v1/api/test/sample/detail.json",    "title": "DownLoad.java",    "version": "1.0.0",    "name": "DownLoad_java",    "group": "com_nssoft_api_test_sample",    "parameter": {      "fields": {        "Parameter": [          {            "group": "Parameter",            "type": "<p>String</p> ",            "optional": true,            "field": "a",            "description": "<p>可选参数x.</p> "          },          {            "group": "Parameter",            "type": "<p>Number</p> ",            "optional": true,            "field": "b",            "defaultValue": "18",            "description": "<p>可选参数的默认值为'18'.</p> "          },          {            "group": "Parameter",            "type": "<p>String</p> ",            "optional": false,            "field": "c",            "description": "<p>必填参数z.</p> "          },          {            "group": "Parameter",            "type": "<p>String</p> ",            "optional": false,            "field": "d",            "defaultValue": "D",            "description": "<p>必填参数的默认值为'D'.</p> "          }        ]      }    },    "sampleRequest": [      {        "url": "/v1/api/test/sample/detail.json"      }    ],    "filename": "nssoft-template/src/main/java/com/nssoft/api/test/sample/DownLoad.java",    "groupTitle": "com_nssoft_api_test_sample"  },  {    "type": "post",    "url": "/v1/api/test/sample/excel.excel",    "title": "Excel.java",    "version": "1.0.0",    "name": "Excel_java",    "group": "com_nssoft_api_test_sample",    "parameter": {      "fields": {        "Parameter": [          {            "group": "Parameter",            "type": "<p>String</p> ",            "optional": true,            "field": "a",            "description": "<p>可选参数x.</p> "          },          {            "group": "Parameter",            "type": "<p>Number</p> ",            "optional": true,            "field": "b",            "defaultValue": "18",            "description": "<p>可选参数的默认值为'18'.</p> "          },          {            "group": "Parameter",            "type": "<p>String</p> ",            "optional": false,            "field": "c",            "description": "<p>必填参数z.</p> "          },          {            "group": "Parameter",            "type": "<p>String</p> ",            "optional": false,            "field": "d",            "defaultValue": "D",            "description": "<p>必填参数的默认值为'D'.</p> "          }        ]      }    },    "sampleRequest": [      {        "url": "/v1/api/test/sample/excel.excel"      }    ],    "filename": "nssoft-template/src/main/java/com/nssoft/api/test/sample/Excel.java",    "groupTitle": "com_nssoft_api_test_sample"  },  {    "type": "post",    "url": "/v1/api/test/sample/fileupload.form",    "title": "FileUpload.java",    "version": "1.0.0",    "name": "FileUpload_java",    "group": "com_nssoft_api_test_sample",    "parameter": {      "fields": {        "Parameter": [          {            "group": "Parameter",            "type": "<p>String</p> ",            "optional": true,            "field": "a",            "description": "<p>可选参数x.</p> "          },          {            "group": "Parameter",            "type": "<p>Number</p> ",            "optional": true,            "field": "b",            "defaultValue": "18",            "description": "<p>可选参数的默认值为'18'.</p> "          },          {            "group": "Parameter",            "type": "<p>String</p> ",            "optional": false,            "field": "c",            "description": "<p>必填参数z.</p> "          },          {            "group": "Parameter",            "type": "<p>String</p> ",            "optional": false,            "field": "d",            "defaultValue": "D",            "description": "<p>必填参数的默认值为'D'.</p> "          }        ]      }    },    "sampleRequest": [      {        "url": "/v1/api/test/sample/fileupload.form"      }    ],    "filename": "nssoft-template/src/main/java/com/nssoft/api/test/sample/FileUpload.java",    "groupTitle": "com_nssoft_api_test_sample"  },  {    "type": "post",    "url": "/v1/api/test/sample/form.json",    "title": "Form.java",    "version": "1.0.0",    "name": "Form_java",    "group": "com_nssoft_api_test_sample",    "parameter": {      "fields": {        "Parameter": [          {            "group": "Parameter",            "type": "<p>String</p> ",            "optional": false,            "field": "name",            "description": "<p>姓名</p> "          },          {            "group": "Parameter",            "type": "<p>String</p> ",            "optional": false,            "field": "email",            "description": "<p>邮箱</p> "          },          {            "group": "Parameter",            "type": "<p>String</p> ",            "optional": false,            "field": "tel",            "description": "<p>电话</p> "          },          {            "group": "Parameter",            "type": "<p>String</p> ",            "optional": false,            "field": "address",            "description": "<p>地址</p> "          },          {            "group": "Parameter",            "type": "<p>String</p> ",            "optional": false,            "field": "gender",            "description": "<p>性别</p> "          },          {            "group": "Parameter",            "type": "<p>String</p> ",            "optional": false,            "field": "birthday",            "description": "<p>生日</p> "          }        ]      }    },    "sampleRequest": [      {        "url": "/v1/api/test/sample/form.json"      }    ],    "filename": "nssoft-template/src/main/java/com/nssoft/api/test/sample/Form.java",    "groupTitle": "com_nssoft_api_test_sample"  },  {    "type": "post",    "url": "/v1/api/test/sample/table.json",    "title": "Table.java",    "version": "1.0.0",    "name": "Table_java",    "group": "com_nssoft_api_test_sample",    "parameter": {      "fields": {        "Parameter": [          {            "group": "Parameter",            "type": "<p>String</p> ",            "optional": true,            "field": "a",            "description": "<p>可选参数x.</p> "          },          {            "group": "Parameter",            "type": "<p>Number</p> ",            "optional": true,            "field": "b",            "defaultValue": "18",            "description": "<p>可选参数的默认值为'18'.</p> "          },          {            "group": "Parameter",            "type": "<p>String</p> ",            "optional": false,            "field": "c",            "description": "<p>必填参数z.</p> "          },          {            "group": "Parameter",            "type": "<p>String</p> ",            "optional": false,            "field": "d",            "defaultValue": "D",            "description": "<p>必填参数的默认值为'D'.</p> "          }        ]      }    },    "sampleRequest": [      {        "url": "/v1/api/test/sample/table.json"      }    ],    "filename": "nssoft-template/src/main/java/com/nssoft/api/test/sample/Table.java",    "groupTitle": "com_nssoft_api_test_sample"  },  {    "type": "post",    "url": "/v1/api/test/sample/updateRow.json",    "title": "UpdateRow.java",    "version": "1.0.0",    "name": "UpdateRow_java",    "group": "com_nssoft_api_test_sample",    "parameter": {      "fields": {        "Parameter": [          {            "group": "Parameter",            "type": "<p>String</p> ",            "optional": true,            "field": "a",            "description": "<p>可选参数x.</p> "          },          {            "group": "Parameter",            "type": "<p>Number</p> ",            "optional": true,            "field": "b",            "defaultValue": "18",            "description": "<p>可选参数的默认值为'18'.</p> "          },          {            "group": "Parameter",            "type": "<p>String</p> ",            "optional": false,            "field": "c",            "description": "<p>必填参数z.</p> "          },          {            "group": "Parameter",            "type": "<p>String</p> ",            "optional": false,            "field": "d",            "defaultValue": "D",            "description": "<p>必填参数的默认值为'D'.</p> "          }        ]      }    },    "sampleRequest": [      {        "url": "/v1/api/test/sample/updateRow.json"      }    ],    "filename": "nssoft-template/src/main/java/com/nssoft/api/test/sample/UpdateRow.java",    "groupTitle": "com_nssoft_api_test_sample"  }]